CustomDiagramIcons/__init__.py
CustomDiagramIcons/common.py
CustomDiagramIcons/generic.py
CustomDiagramIcons/module1.py
CustomDiagramIcons/module2.py
CustomDiagramIcons/icons/__init__.py
CustomDiagramIcons/icons/crim_team_icon.png
CustomDiagramIcons/icons/crim_tools_icon.png
CustomDiagramIcons/icons/github_icon.png
CustomDiagramIcons/icons/jira_icon.png
CustomDiagramIcons/icons/octopus_deploy_icon.png
CustomDiagramIcons/icons/octopus_server_node_icon.png
CustomDiagramIcons/icons/octopus_worker_node_icon.png
CustomDiagramIcons/icons/octopus_worker_pool_icon.png
CustomDiagramIcons/icons/pipeline_icon.png
CustomDiagramIcons/icons/release_icon.png
CustomDiagramIcons/icons/software_engineer_icon.png
CustomDiagramIcons/onprem/__init__.py
CustomDiagramIcons/onprem/cd/__init__.py
CustomDiagramIcons/onprem/cd/octopusDeploy.py
tests/__init__.py
tests/test_module1.py
tests/test_module2.py
CustomDiagramIcons-1.0.0.dist-info/LICENSE
CustomDiagramIcons-1.0.0.dist-info/METADATA
CustomDiagramIcons-1.0.0.dist-info/WHEEL
CustomDiagramIcons-1.0.0.dist-info/top_level.txt
CustomDiagramIcons-1.0.0.dist-info/RECORD
