Metadata-Version: 2.1
Name: CustomDiagramIcons
Version: 1.0.0
Summary: This is intended to be used in a project that uses the diagrams (diagrams as code) python package as an extention of the icons.
Home-page: UNKNOWN
Author: Joshua Duma
Author-email: joshua.duma@trader.ca
License: UNKNOWN
Platform: UNKNOWN
Classifier: Programming Language :: Python :: 3
Classifier: License :: OSI Approved :: MIT License
Classifier: Operating System :: OS Independent
Requires-Python: >=3.6
License-File: LICENSE
Requires-Dist: diagrams >=0.23.4
